{
  "data":[
    {
      "id": 1,
      "owner": {
        "id": 555,
        "name": "Alisa"
      },
      "created_at": "",
      "what_did":
      [
       {
        "id": 3,
        "title": "Create database",
        "status": "deactive"
       },
       {
        "id": 4,
        "title": "Add method update to database",
        "status": "active"
       }
      ],
      "todo": [

       {
        "id": 4,
        "title": "Add methods update to database",
        "status": "active"
       },
       {
        "id": 6,
        "title": "Add methods delete to database",
        "status": "active"
       }
      ],
      "problems": "",
      "deadline": true,
      "reason": ""
    },
    {
      "id": 2,
      "owner": {
        "id": 2,
        "name": "Bob"
      },
      "created_at": "",
      "what_did":
      [
       {
        "id": 5,
        "title": "Describe architecture of project",
        "status": "deactive"
       },
       {
        "id": 7,
        "title": "Add class of objct Word",
        "status": "deactive"
       },
       {
        "id": 8,
        "title": "Add class of object Dictionary",
        "status": "deactive"
       }
      ],
      "todo": [

       {
        "id": 9,
        "title": "Update methods update to database",
        "status": "active"
       }
      ],
      "problems": "",
      "deadline": true,
      "reason": ""
    },
    {
      "id": 3,
      "owner": {
        "id": 555,
        "name": "Alisa"
      },
      "created_at": "",
      "what_did":
      [
       {
        "id": 4,
        "title": "Add methods update to database",
        "status": "deactive"
       },
       {
        "id": 6,
        "title": "Add methods delete to database",
        "status": "active"
       }
      ],
      "todo": [
       {
        "id": 6,
        "title": "Add methods delete to database",
        "status": "active"
       },
      {
        "id": 10,
        "title": "Add methods create to database",
        "status": "active"
       }
      ],
      "problems": "",
      "deadline": true,
      "reason": ""
    },
    {
      "id": 4,
      "owner": {
        "id": 2,
        "name": "Bob"
      },
      "created_at": "",
      "what_did":
      [
       {
        "id": 9,
        "title": "Update methods update to database",
        "status": "deactive"
       }
      ],
      "todo": [

       {
        "id": 666,
        "title": "Relax at weekand :)",
        "status": "active"
       }
      ],
      "problems": "",
      "deadline": true,
      "reason": ""
    }
  ]
}
